lfs_compropago/__init__.py
lfs_compropago/admin.py
lfs_compropago/currency.py
lfs_compropago/models.py
lfs_compropago/tests.py
lfs_compropago/urls.py
lfs_compropago/views.py
lfs_compropago/static/compropago/payment-green-btn.png
lfs_compropago/static/compropago/logos/bodega-aurrera.png
lfs_compropago/static/compropago/logos/chedraui.png
lfs_compropago/static/compropago/logos/coppel.jpg
lfs_compropago/static/compropago/logos/coppel.png
lfs_compropago/static/compropago/logos/el-porton.png
lfs_compropago/static/compropago/logos/elektra.png
lfs_compropago/static/compropago/logos/extra.png
lfs_compropago/static/compropago/logos/farmacia_benavides.png
lfs_compropago/static/compropago/logos/farmacia_esquivar.png
lfs_compropago/static/compropago/logos/farmacia_guadalajara.png
lfs_compropago/static/compropago/logos/oxxo.png
lfs_compropago/static/compropago/logos/sams-club.png
lfs_compropago/static/compropago/logos/seven_eleven.png
lfs_compropago/static/compropago/logos/soriana.png
lfs_compropago/static/compropago/logos/superama.png
lfs_compropago/static/compropago/logos/vips.png
lfs_compropago/static/compropago/logos/walmart.png
lfs_compropago/templates/compropago/payment_instructions.html
lfs_compropago/templates/compropago/payment_method.html
lfs_compropago/templates/compropago/transaction_state.html
lfs_compropago-0.4.3.dist-info/DESCRIPTION.rst
lfs_compropago-0.4.3.dist-info/METADATA
lfs_compropago-0.4.3.dist-info/RECORD
lfs_compropago-0.4.3.dist-info/WHEEL
lfs_compropago-0.4.3.dist-info/metadata.json
lfs_compropago-0.4.3.dist-info/top_level.txt
