Metadata-Version: 2.0
Name: lfs-compropago
Version: 0.4.3
Summary: ComproPago payment processor for Django-LFS
Home-page: http://github.io/tzicatl/lfs-compropago
Author: Noe Nieto
Author-email: nnieto@noenieto.com
License: MIT
Keywords: ecommerce e-commerce payment development mexico lfs django-lfs
Platform: UNKNOWN
Classifier: Development Status :: 4 - Beta
Classifier: Environment :: No Input/Output (Daemon)
Classifier: Environment :: Web Environment
Classifier: Intended Audience :: Developers
Classifier: License :: OSI Approved :: MIT License
Classifier: Natural Language :: Spanish
Classifier: Operating System :: OS Independent
Classifier: Programming Language :: Python :: 2.7
Requires-Dist: beautifulsoup4
Requires-Dist: compropago-python (>=0.2)
Requires-Dist: lxml
Requires-Dist: python-dateutil
Requires-Dist: suds
